vector_lake/__init__.py
vector_lake/__main__.py
vector_lake/core/__init__.py
vector_lake/core/hnsw.py
vector_lake/core/index.py
vector_lake/langchain/__init__.py
vector_lake-0.0.5.dist-info/METADATA
vector_lake-0.0.5.dist-info/WHEEL
vector_lake-0.0.5.dist-info/entry_points.txt
vector_lake-0.0.5.dist-info/licenses/LICENSE
vector_lake-0.0.5.dist-info/RECORD
