Metadata-Version: 2.4
Name: vector_lake
Version: 0.0.5
Summary: S3 vector database for bigdata
License: MIT
License-File: LICENSE
Keywords: vector,database,bigdata
Author: Alexander Miasoiedov
Author-email: msoedov@gmail.com
Maintainer: Alexander Miasoiedov
Maintainer-email: msoedov@gmail.com
Requires-Python: >=3.9,<4.0
Classifier: License :: OSI Approved :: MIT License
Classifier: Programming Language :: Python :: 3
Classifier: Programming Language :: Python :: 3.9
Classifier: Programming Language :: Python :: 3.10
Classifier: Programming Language :: Python :: 3.11
Classifier: Programming Language :: Python :: 3.12
Classifier: Programming Language :: Python :: 3.13
Classifier: Programming Language :: Python :: 3.14
Provides-Extra: dev
Provides-Extra: s3
Requires-Dist: black (>=24.4.2,<25.0.0) ; extra == "dev"
Requires-Dist: boto3 (>=1.34.115,<2.0.0) ; extra == "s3"
Requires-Dist: fire (>=0.5.0,<0.6.0)
Requires-Dist: httpx (>=0.27.0,<0.28.0) ; extra == "dev"
Requires-Dist: hypothesis (>=6.99.13,<7.0.0) ; extra == "dev"
Requires-Dist: loguru (>=0.7.0,<0.8.0)
Requires-Dist: mypy (>=1.10.0,<2.0.0) ; extra == "dev"
Requires-Dist: numpy (>=1.26.4,<2.0.0)
Requires-Dist: pandas (>=2.2.2,<3.0.0)
Requires-Dist: pre-commit (>=3.7.1,<4.0.0) ; extra == "dev"
Requires-Dist: pyarrow (>=16.1.0,<17.0.0)
Requires-Dist: pydantic (>=1.10.15,<2.0.0)
Requires-Dist: pytest (>=8.2.0,<9.0.0) ; extra == "dev"
Requires-Dist: pytest-benchmark (==4.0.0) ; extra == "dev"
Requires-Dist: pytz (>=2024.1,<2025.0)
Requires-Dist: scikit-learn (>=1.4.2,<2.0.0)
Requires-Dist: types-requests (>=2.31.0,<3.0.0) ; extra == "dev"
Project-URL: Repository, https://github.com/msoedov/vector_lake
